com/__init__.py
com/johnsnowlabs/__init__.py
com/johnsnowlabs/extensions/__init__.py
com/johnsnowlabs/extensions/finance/__init__.py
com/johnsnowlabs/nlp/__init__.py
sparknlp_jsl/__init__.py
sparknlp_jsl/base.py
sparknlp_jsl/compatibility.py
sparknlp_jsl/custom_transformer.py
sparknlp_jsl/eval.py
sparknlp_jsl/freeze.py
sparknlp_jsl/functions.py
sparknlp_jsl/internal.py
sparknlp_jsl/pretrained.py
sparknlp_jsl/structured_deidentification.py
sparknlp_jsl/text_to_documents_columns.py
sparknlp_jsl/training.py
sparknlp_jsl/updateModels.py
sparknlp_jsl/util.py
sparknlp_jsl/_tf_graph_builders/__init__.py
sparknlp_jsl/_tf_graph_builders/graph_builders.py
sparknlp_jsl/_tf_graph_builders/assertion_dl/__init__.py
sparknlp_jsl/_tf_graph_builders/assertion_dl/assertion_model.py
sparknlp_jsl/_tf_graph_builders/generic_classifier/__init__.py
sparknlp_jsl/_tf_graph_builders/generic_classifier/basetfmodel.py
sparknlp_jsl/_tf_graph_builders/generic_classifier/build_model.py
sparknlp_jsl/_tf_graph_builders/generic_classifier/generic_classifier_model.py
sparknlp_jsl/_tf_graph_builders/generic_classifier/progresstracker.py
sparknlp_jsl/_tf_graph_builders/generic_classifier/settings.py
sparknlp_jsl/_tf_graph_builders/ner_dl/__init__.py
sparknlp_jsl/_tf_graph_builders/ner_dl/create_graph.py
sparknlp_jsl/_tf_graph_builders/ner_dl/dataset_encoder.py
sparknlp_jsl/_tf_graph_builders/ner_dl/ner_model.py
sparknlp_jsl/_tf_graph_builders/ner_dl/ner_model_saver.py
sparknlp_jsl/_tf_graph_builders/ner_dl/sentence_grouper.py
sparknlp_jsl/_tf_graph_builders/tf2contrib/__init__.py
sparknlp_jsl/_tf_graph_builders/tf2contrib/core_rnn_cell.py
sparknlp_jsl/_tf_graph_builders/tf2contrib/fused_rnn_cell.py
sparknlp_jsl/_tf_graph_builders/tf2contrib/gru_ops.py
sparknlp_jsl/_tf_graph_builders/tf2contrib/lstm_ops.py
sparknlp_jsl/_tf_graph_builders/tf2contrib/rnn.py
sparknlp_jsl/_tf_graph_builders/tf2contrib/rnn_cell.py
sparknlp_jsl/_tf_graph_builders_1x/__init__.py
internal_with_fin_tmp-0.1.5.dist-info/METADATA
internal_with_fin_tmp-0.1.5.dist-info/WHEEL
internal_with_fin_tmp-0.1.5.dist-info/top_level.txt
internal_with_fin_tmp-0.1.5.dist-info/RECORD
